{
  "version": "0.1.0",
  "name": "koala_program",
  "instructions": [
    {
      "name": "initializeStakeAccount",
      "accounts": [
        {
          "name": "owner",
          "isMut": true,
          "isSigner": true
        },
        {
          "name": "stakeAccount",
          "isMut": true,
          "isSigner": false
        },
        {
          "name": "systemProgram",
          "isMut": false,
          "isSigner": false
        },
        {
          "name": "rent",
          "isMut": false,
          "isSigner": false
        }
      ],
      "args": [
        {
          "name": "bump",
          "type": "u8"
        }
      ]
    },
    {
      "name": "stakeNft",
      "accounts": [
        {
          "name": "owner",
          "isMut": true,
          "isSigner": true
        },
        {
          "name": "stakeAccount",
          "isMut": true,
          "isSigner": false
        },
        {
          "name": "nftMint",
          "isMut": false,
          "isSigner": false
        },
        {
          "name": "nftTokenAccount",
          "isMut": true,
          "isSigner": false
        },
        {
          "name": "tokenProgram",
          "isMut": false,
          "isSigner": false
        },
        {
          "name": "systemProgram",
          "isMut": false,
          "isSigner": false
        },
        {
          "name": "rent",
          "isMut": false,
          "isSigner": false
        },
        {
          "name": "clock",
          "isMut": false,
          "isSigner": false
        }
      ],
      "args": []
    },
    {
      "name": "unstakeNft",
      "accounts": [
        {
          "name": "owner",
          "isMut": true,
          "isSigner": true
        },
        {
          "name": "stakeAccount",
          "isMut": true,
          "isSigner": false
        },
        {
          "name": "nftMint",
          "isMut": false,
          "isSigner": false
        },
        {
          "name": "nftTokenAccount",
          "isMut": true,
          "isSigner": false
        },
        {
          "name": "tokenProgram",
          "isMut": false,
          "isSigner": false
        },
        {
          "name": "clock",
          "isMut": false,
          "isSigner": false
        }
      ],
      "args": []
    }
  ],
  "accounts": [
    {
      "name": "NftStakeAccount",
      "type": {
        "kind": "struct",
        "fields": [
          {
            "name": "owner",
            "type": "publicKey"
          },
          {
            "name": "numStaked",
            "type": "u16"
          },
          {
            "name": "bump",
            "type": "u8"
          },
          {
            "name": "lastClaimed",
            "type": "i64"
          }
        ]
      }
    }
  ],
  "errors": [
    {
      "code": 6000,
      "name": "InvalidStakedNFTOwner"
    },
    {
      "code": 6001,
      "name": "InvalidNFTAccountMint"
    },
    {
      "code": 6002,
      "name": "InvalidNFTMintSupply"
    },
    {
      "code": 6003,
      "name": "InvalidOwnerForStakeAccount"
    },
    {
      "code": 6004,
      "name": "InvalidNFTOwner"
    },
    {
      "code": 6005,
      "name": "NFTAccountEmpty"
    }
  ],
  "metadata": {
    "address": "8QUWf8UVcyfQMj8iFaXHSpkWKjcnZuSpTMkphV72Zv3Y"
  }
}